{
  "id": "Nahida",
  "shareid": 49,
  "name": "Nahida",
  "title": "Natürliche Reinheit – Nahida",
  "desc": "Natürliche Reinheit und Frühlingerwachen in den Tiefen des Palasts.",
  "attributes": {
    "hp": 10,
    "cardType": "Figurenkarte",
    "energy": 2,
    "element": "Dendro",
    "weapon": "Katalysator",
    "faction": [
      "Sumeru",
      "Sumeru"
    ],
    "talentCard": {
      "id": "TheSeedOfStoredKnowledge",
      "name": "The Seed of Stored Knowledge"
    },
    "source": "Nach einem gewonnenen „Duell – Nett“ mit Nahida in der Taverne Zum Katzenschwanz zu erhalten.",
    "character": {
      "id": "Nahida",
      "name": "Nahida",
      "rarity": 5
    }
  },
  "skills": [
    {
      "id": "Akara",
      "name": "Akara",
      "desc": "Verursacht 1 Pkt. Dendro-SCH.",
      "skilltag": [
        "Standardangriff"
      ],
      "points": [
        {
          "id": "Dendro",
          "type": "Dendro",
          "count": 1
        },
        {
          "id": "UnalignedElement",
          "type": "Würfel (beliebig)",
          "count": 2
        }
      ]
    },
    {
      "id": "AllSchemesToKnow",
      "name": "Kennerin aller Tricks",
      "desc": "Verursacht 2 Pkt. Dendro-SCH, verleiht dem Ziel Samen von Skandha; ist das Ziel allerdings bereits von Samen von Skandha betroffen, verleiht dann allen Figuren des Gegners Samen von Skandha.",
      "skilltag": [
        "Elementarfähigkeit"
      ],
      "points": [
        {
          "id": "Dendro",
          "type": "Dendro",
          "count": 3
        }
      ]
    },
    {
      "id": "AllSchemesToKnowTathata",
      "name": "Kennerin aller Tricks – Tathata",
      "desc": "Verursacht 3 Pkt. Dendro-SCH, verleiht allen Figuren des Gegners Samen von Skandha.",
      "skilltag": [
        "Elementarfähigkeit"
      ],
      "points": [
        {
          "id": "Dendro",
          "type": "Dendro",
          "count": 5
        }
      ]
    },
    {
      "id": "IllusoryHeart",
      "name": "Illusorisches Herz",
      "desc": "Verursacht 4 Pkt. Dendro-SCH, erschafft 1 Schrein von Maya.",
      "skilltag": [
        "Spezialfähigkeit"
      ],
      "points": [
        {
          "id": "Dendro",
          "type": "Dendro",
          "count": 3
        },
        {
          "id": "Energy",
          "type": "Aufladung",
          "count": 2
        }
      ]
    },
    {
      "id": "Akara",
      "name": "Akara",
      "desc": "Verursacht 1 Pkt. Dendro-SCH.",
      "skillTag": [
        "Standardangriff"
      ],
      "points": [
        {
          "id": "Dendro",
          "type": "Dendro",
          "count": 1
        },
        {
          "id": "UnalignedElement",
          "type": "Würfel (beliebig)",
          "count": 2
        }
      ]
    },
    {
      "id": "AllSchemesToKnow",
      "name": "Kennerin aller Tricks",
      "desc": "Verursacht 2 Pkt. Dendro-SCH, verleiht dem Ziel Samen von Skandha; ist das Ziel allerdings bereits von Samen von Skandha betroffen, verleiht dann allen Figuren des Gegners Samen von Skandha.",
      "skillTag": [
        "Elementarfähigkeit"
      ],
      "points": [
        {
          "id": "Dendro",
          "type": "Dendro",
          "count": 3
        }
      ]
    },
    {
      "id": "AllSchemesToKnowTathata",
      "name": "Kennerin aller Tricks – Tathata",
      "desc": "Verursacht 3 Pkt. Dendro-SCH, verleiht allen Figuren des Gegners Samen von Skandha.",
      "skillTag": [
        "Elementarfähigkeit"
      ],
      "points": [
        {
          "id": "Dendro",
          "type": "Dendro",
          "count": 5
        }
      ]
    },
    {
      "id": "IllusoryHeart",
      "name": "Illusorisches Herz",
      "desc": "Verursacht 4 Pkt. Dendro-SCH, erschafft 1 Schrein von Maya.",
      "skillTag": [
        "Spezialfähigkeit"
      ],
      "points": [
        {
          "id": "Dendro",
          "type": "Dendro",
          "count": 3
        },
        {
          "id": "Energy",
          "type": "Aufladung",
          "count": 2
        }
      ]
    }
  ],
  "version": "4.4",
  "shareId": 49
}