{
  "id": "Diona",
  "shareId": 2,
  "name": "Диона",
  "title": "«Кошкин Коктейль» Диона",
  "desc": "1% сил уходит на смешивание коктейля, а 99% на отрицание провала...",
  "attributes": {
    "hp": 10,
    "card_type": "Карты персонажей",
    "energy": 3,
    "element": "Крио",
    "weapon": "Стрелковое",
    "faction": [
      "Мондштадт"
    ],
    "source": "Награда за приглашение Дионы в «Кошкин хвост» и победу над ней в Дружеской дуэли",
    "character": {
      "id": "Diona",
      "name": "Diona",
      "rarity": 4
    }
  },
  "skills": [
    {
      "id": "KtzleinStyle",
      "name": "Стиль котёнка",
      "desc": "Наносит Физический урон, 2 ед.",
      "skillTag": [
        "Обычная атака"
      ],
      "points": [
        {
          "id": "Cryo",
          "type": "Крио",
          "count": 1
        },
        {
          "id": "UnalignedElement",
          "type": "Неопределённый элемент",
          "count": 2
        }
      ]
    },
    {
      "id": "IcyPaws",
      "name": "Морозные коготочки",
      "desc": "Наносит Крио урон, 2 ед. и создаёт Щит кошачьих коготочков.",
      "skillTag": [
        "Элементальный навык"
      ],
      "points": [
        {
          "id": "Cryo",
          "type": "Крио",
          "count": 3
        }
      ]
    },
    {
      "id": "SignatureMix",
      "name": "Авторский коктейль",
      "desc": "Наносит Крио урон, 1 ед., исцеляет 2 HP персонажа, призывает помощника: Пьянящий туман.",
      "skillTag": [
        "Взрыв стихии"
      ],
      "points": [
        {
          "id": "Cryo",
          "type": "Крио",
          "count": 3
        },
        {
          "id": "Energy",
          "type": "Энергия",
          "count": 3
        }
      ]
    }
  ],
  "version": "3.4"
}