{
	"id": "Halberd",
	"name": "Alabarda",
	"description": "Un arma de asta con una hoja de hacha montada en la parte superior, capaz de causar mucho da\u00f1o. El arma predilecta entre los oficiales de la Geoarmada.",
	"rarity": 3,
	"type": "Lanza",
	"domain": "Palacio oculto de la f\u00f3rmula Lianshan",
	"passive": "Pesado",
	"bonus": "Los Ataques Normales infligen un 160%/200%/240%/280%/320% de da\u00f1o adicional a los enemigos. Este efecto solo puede ocurrir una vez cada 10 s.",
	"stats": {
		"primary": "ATQ B\u00e1sico",
		"secondary": "ATQ%",
		"levels": [
			{
				"ascension": 0,
				"level": 1,
				"primary": 40,
				"secondary": 5.1
			},
			{
				"ascension": 0,
				"level": 20,
				"primary": 102,
				"secondary": 9
			},
			{
				"ascension": 1,
				"level": 20,
				"primary": 121,
				"secondary": 9
			},
			{
				"ascension": 1,
				"level": 40,
				"primary": 187,
				"secondary": 13.1
			},
			{
				"ascension": 2,
				"level": 40,
				"primary": 207,
				"secondary": 13.1
			},
			{
				"ascension": 2,
				"level": 50,
				"primary": 239,
				"secondary": 15.2
			},
			{
				"ascension": 3,
				"level": 50,
				"primary": 259,
				"secondary": 15.2
			},
			{
				"ascension": 3,
				"level": 60,
				"primary": 292,
				"secondary": 17.3
			},
			{
				"ascension": 4,
				"level": 60,
				"primary": 311,
				"secondary": 17.3
			},
			{
				"ascension": 4,
				"level": 70,
				"primary": 344,
				"secondary": 19.3
			},
			{
				"ascension": 5,
				"level": 70,
				"primary": 363,
				"secondary": 19.3
			},
			{
				"ascension": 5,
				"level": 80,
				"primary": 396,
				"secondary": 21.4
			},
			{
				"ascension": 6,
				"level": 80,
				"primary": 415,
				"secondary": 21.4
			},
			{
				"ascension": 6,
				"level": 90,
				"primary": 448,
				"secondary": 23.5
			}
		]
	},
	"ascensions": [
		{
			"ascension": 0,
			"level": 20,
			"materials": []
		},
		{
			"ascension": 1,
			"level": 40,
			"cost": 5000,
			"materials": [
				{
					"id": "MistVeiledLeadElixir",
					"name": "Perdigones de plomo",
					"amount": 2,
					"rarity": 2
				},
				{
					"id": "MistGrassPollen",
					"name": "Polen neblinoso",
					"amount": 2,
					"rarity": 2
				},
				{
					"id": "WhopperflowerNectar",
					"name": "N\u00e9ctar de Megaflora",
					"amount": 1,
					"rarity": 1
				}
			]
		},
		{
			"ascension": 2,
			"level": 50,
			"cost": 10000,
			"materials": [
				{
					"id": "MistVeiledMercuryElixir",
					"name": "Perdigones de mercurio",
					"amount": 2,
					"rarity": 3
				},
				{
					"id": "MistGrassPollen",
					"name": "Polen neblinoso",
					"amount": 8,
					"rarity": 2
				},
				{
					"id": "WhopperflowerNectar",
					"name": "N\u00e9ctar de Megaflora",
					"amount": 5,
					"rarity": 1
				}
			]
		},
		{
			"ascension": 3,
			"level": 60,
			"cost": 15000,
			"materials": [
				{
					"id": "MistVeiledMercuryElixir",
					"name": "Perdigones de mercurio",
					"amount": 4,
					"rarity": 3
				},
				{
					"id": "MistGrass",
					"name": "Hierba neblinosa",
					"amount": 4,
					"rarity": 3
				},
				{
					"id": "ShimmeringNectar",
					"name": "N\u00e9ctar brillante",
					"amount": 4,
					"rarity": 2
				}
			]
		},
		{
			"ascension": 4,
			"level": 70,
			"cost": 20000,
			"materials": [
				{
					"id": "MistVeiledGoldElixir",
					"name": "Perdigones de oro",
					"amount": 2,
					"rarity": 4
				},
				{
					"id": "MistGrass",
					"name": "Hierba neblinosa",
					"amount": 8,
					"rarity": 3
				},
				{
					"id": "ShimmeringNectar",
					"name": "N\u00e9ctar brillante",
					"amount": 6,
					"rarity": 2
				}
			]
		},
		{
			"ascension": 5,
			"level": 80,
			"cost": 25000,
			"materials": [
				{
					"id": "MistVeiledGoldElixir",
					"name": "Perdigones de oro",
					"amount": 4,
					"rarity": 4
				},
				{
					"id": "MistGrassWick",
					"name": "L\u00e1mpara de hierba neblinosa",
					"amount": 6,
					"rarity": 4
				},
				{
					"id": "EnergyNectar",
					"name": "N\u00e9ctar energ\u00e9tico",
					"amount": 4,
					"rarity": 3
				}
			]
		},
		{
			"ascension": 6,
			"level": 90,
			"cost": 30000,
			"materials": [
				{
					"id": "MistVeiledPrimoElixir",
					"name": "Perdigones primordiales",
					"amount": 3,
					"rarity": 5
				},
				{
					"id": "MistGrassWick",
					"name": "L\u00e1mpara de hierba neblinosa",
					"amount": 12,
					"rarity": 4
				},
				{
					"id": "EnergyNectar",
					"name": "N\u00e9ctar energ\u00e9tico",
					"amount": 8,
					"rarity": 3
				}
			]
		}
	],
	"refinement_raw": {
		"name": "Pesado",
		"template": "Los Ataques Normales infligen un <span style=\"color:#99FFFFFF\">{0} de da\u00f1o adicional a los enemigos. Este efecto solo puede ocurrir una vez cada 10 s.",
		"params": [["160%"], ["200%"], ["240%"], ["280%"], ["320%"]]
	},
	"refinements": [
		{
			"refinement": 1,
			"desc": "Los Ataques Normales infligen un 160% de da\u00f1o adicional a los enemigos. Este efecto solo puede ocurrir una vez cada 10 s."
		},
		{
			"refinement": 2,
			"desc": "Los Ataques Normales infligen un 200% de da\u00f1o adicional a los enemigos. Este efecto solo puede ocurrir una vez cada 10 s."
		},
		{
			"refinement": 3,
			"desc": "Los Ataques Normales infligen un 240% de da\u00f1o adicional a los enemigos. Este efecto solo puede ocurrir una vez cada 10 s."
		},
		{
			"refinement": 4,
			"desc": "Los Ataques Normales causan un 280% adicional de da\u00f1o a los oponentes. Este efecto puede activarse una vez cada 10 s."
		},
		{
			"refinement": 5,
			"desc": "Los Ataques Normales infligen un 320% de da\u00f1o adicional a los enemigos. Este efecto solo puede ocurrir una vez cada 10 s."
		}
	],
	"pictures": {
		"icon": "Weapon/Halberd/Icon.webp"
	}
}
