{
  "id": "Candace",
  "shareId": 15,
  "name": "Candace",
  "title": "บุหลันดั้นปฏิญาณ - Candace",
  "desc": "ทรายสีชาดประกายทอง ผู้สาบานเพื่อการปกป้อง",
  "attributes": {
    "hp": 10,
    "card_type": "การ์ดตัวละคร",
    "energy": 2,
    "element": "ธาตุน้ำ",
    "weapon": "หอก",
    "faction": [
      "Sumeru"
    ],
    "talent_card": {
      "id": "TheOverflow",
      "name": "The Overflow"
    },
    "source": "ได้รับหลังจากเชิญ Candace ทำการดูเอลใน Cat's Tail และเอาชนะในระดับความยากฉันมิตร",
    "character": {
      "id": "Candace",
      "name": "Candace",
      "rarity": 4
    }
  },
  "skills": [
    {
      "id": "GleamingSpearGuardianStance",
      "name": "Gleaming Spear - Guardian Stance",
      "desc": "สร้าง<span style=\"color:#FFFFFFFF\">ความเสียหายกายภาพ</span> 2 หน่วย",
      "skillTag": [
        "โจมตีปกติ"
      ],
      "points": [
        {
          "id": "Hydro",
          "type": "ธาตุน้ำ",
          "count": 1
        },
        {
          "id": "UnalignedElement",
          "type": "ธาตุไร้สี",
          "count": 2
        }
      ]
    },
    {
      "id": "SacredRiteHeronsSanctum",
      "name": "Sacred Rite: Heron's Sanctum",
      "desc": "ตัวละครนี้จะได้รับ <span style=\"color:#FFFFFFFF\">Heron Shield</span> และการ<span style=\"color:#FFFFFFFF\">เตรียมสกิล</span>: <span style=\"color:#FFFFFFFF\">Heron Strike</span>",
      "skillTag": [
        "สกิลธาตุ"
      ],
      "points": [
        {
          "id": "Hydro",
          "type": "ธาตุน้ำ",
          "count": 3
        }
      ]
    },
    {
      "id": "SacredRiteWagtailsTide",
      "name": "Sacred Rite: Wagtail's Tide",
      "desc": "สร้าง<span style=\"color:#80C0FFFF\">ความเสียหายน้ำ</span> 2 หน่วย และสร้าง <span style=\"color:#FFFFFFFF\">Prayer of the Crimson Crown</span>",
      "skillTag": [
        "ท่าไม้ตาย"
      ],
      "points": [
        {
          "id": "Hydro",
          "type": "ธาตุน้ำ",
          "count": 3
        },
        {
          "id": "Energy",
          "type": "พลังงาน",
          "count": 2
        }
      ]
    }
  ],
  "version": "4.2"
}