{
  "id": "Xianyun",
  "shareId": 408,
  "name": "Xianyun",
  "title": "ปักษาสื่อสวรรค์ - Xianyun",
  "desc": "วีรสตรีในเงาเมฆา",
  "attributes": {
    "hp": 10,
    "card_type": "การ์ดตัวละคร",
    "energy": 2,
    "element": "ธาตุลม",
    "weapon": "สื่อเวท",
    "faction": [
      "Liyue"
    ],
    "source": "ได้รับหลังจากเชิญ Xianyun ทำการดูเอลใน Cat's Tail และเอาชนะในระดับความยากฉันมิตร"
  },
  "skills": [
    {
      "id": "WordOfWindAndFlower",
      "name": "Word of Wind and Flower",
      "desc": "สร้าง<span style=\"color:#80FFD7FF\">ความเสียหายลม</span> 1 หน่วย",
      "skillTag": [
        "โจมตีปกติ"
      ],
      "points": [
        {
          "id": "Anemo",
          "type": "ธาตุลม",
          "count": 1
        },
        {
          "id": "UnalignedElement",
          "type": "ธาตุไร้สี",
          "count": 2
        }
      ]
    },
    {
      "id": "WhiteCloudsAtDawn",
      "name": "White Clouds at Dawn",
      "desc": "สร้าง<span style=\"color:#80FFD7FF\">ความเสียหายลม</span> 2 หน่วย สร้าง <span style=\"color:#FFFFFFFF\">บันไดสุราลัย</span> และตัวละครนี้จะได้รับ <span style=\"color:#FFFFFFFF\">Driftcloud Wave</span>",
      "skillTag": [
        "สกิลธาตุ"
      ],
      "points": [
        {
          "id": "Anemo",
          "type": "ธาตุลม",
          "count": 3
        }
      ]
    },
    {
      "id": "StarsGatherAtDusk",
      "name": "Stars Gather at Dusk",
      "desc": "สร้าง<span style=\"color:#80FFD7FF\">ความเสียหายลม</span> 1 หน่วย รักษาตัวละครทั้งหมดของฝ่ายเรา 1 หน่วย และทำให้เกิดการ์ด <span style=\"color:#FFFFFFFF\">Starwicker</span><br/>(ตัวละครที่ติดตั้งการ์ด <span style=\"color:#FFFFFFFF\">Starwicker</span> สามารถใช้เทคนิค: <span style=\"color:#FFFFFFFF\">Adeptal Assistance</span>)",
      "skillTag": [
        "ท่าไม้ตาย"
      ],
      "points": [
        {
          "id": "Anemo",
          "type": "ธาตุลม",
          "count": 3
        },
        {
          "id": "Energy",
          "type": "พลังงาน",
          "count": 2
        }
      ]
    }
  ],
  "version": "5.0"
}