{
  "id": "CheckeredCedarCeiling",
  "rarity": 3,
  "name": "Teto Xadrez de Cedro",
  "description": "Um teto de madeira feito de Cedro Fragrante. Simples e adorável, combina perfeitamente com móveis de todos os tipos.\\nO principal uso dos tetos é coletar a poeira que cai das vigas e outras estruturas. Assim, eles ganharam o apelido de \"Coletores de Pó\".\\nDizem que esses apelidos honoríficos são dados a muitas outras coisas em Liyue: cortinas, mesas, cadeiras e até mesmo Mora.",
  "energy": 30,
  "exp": 60,
  "category": [
    {
      "id": 1003,
      "category": "Teto"
    }
  ],
  "recipe": [
    {
      "id": "FragrantCedarWood",
      "name": "Madeira de Cedro Fragrante",
      "amount": 4
    },
    {
      "id": "BlueDye",
      "name": "Tinta Azul",
      "amount": 4
    },
    {
      "id": "RedDye",
      "name": "Tinta Vermelha",
      "amount": 4
    }
  ],
  "version": "3.0"
}