{
  "id": "ControlledDirectionalBlast",
  "shareid": 347,
  "name": "Controlled Directional Blast",
  "title": "Controlled Directional Blast",
  "desc": "\"...ไม่ได้ปิดบังอะไรทั้งนั้น ทั้งหมดถูกจัดการไปเรียบร้อยแล้ว การระเบิดครั้งนี้เป็น 'ระเบิดที่ควบคุมทิศทางการระเบิดได้และไม่เป็นอันตราย'\"",
  "inPlayDescription": "",
  "attributes": {
    "cost": 1,
    "costType": "ธาตุชนิดเดียวกัน",
    "cardType": "การ์ดเหตุการณ์",
    "energy": [
      {
        "id": "MatchingElement",
        "type": "ธาตุชนิดเดียวกัน",
        "count": 1
      },
      {
        "id": "MatchingElement",
        "type": "ธาตุชนิดเดียวกัน",
        "count": 1
      }
    ]
  },
  "skills": [
    {
      "name": "",
      "desc": "จะสามารถใช้ได้ เมื่อจำนวนการ์ดทั้งหมดในพื้นที่สนับสนุน และพื้นที่อัญเชิญของฝ่ายตรงข้ามมีอย่างน้อย 4 ใบ: จำนวนครั้งที่ใช้ได้ของสิ่งอัญเชิญทั้งหมดของทั้งสองฝ่าย -1"
    },
    {
      "name": "",
      "desc": "จะสามารถใช้ได้ เมื่อจำนวนการ์ดทั้งหมดในพื้นที่สนับสนุน และพื้นที่อัญเชิญของฝ่ายตรงข้ามมีอย่างน้อย 4 ใบ: จำนวนครั้งที่ใช้ได้ของสิ่งอัญเชิญทั้งหมดของทั้งสองฝ่าย -1"
    }
  ],
  "version": "4.5",
  "shareId": 347
}