{
  "id": "Timmie",
  "shareid": 200,
  "name": "Timmie",
  "title": "ผู้ปกปักความวิสุทธิ์ - Timmie",
  "desc": "\"นกพิราบที่บินหนีไป จะบินกลับมาอีกมั้ยนะ?\"",
  "inPlayDescription": "",
  "attributes": {
    "cost": 0,
    "cardType": "การ์ดสนับสนุน",
    "energy": [],
    "source": "ได้รับเมื่อสำเร็จเป้าหมายการท้าทายทั้งหมด หลังจากเข้าท้าทายผจญภัยกับผู้เล่น Timmie ในโลกกว้าง",
    "tags": [
      "เพื่อน",
      "เพื่อน"
    ]
  },
  "skills": [
    {
      "name": "",
      "desc": "ในแต่ละเทิร์นจะเกิดขึ้น 1 ครั้ง โดยอัตโนมัติ: การ์ดใบนี้จะสะสม \"Pigeon\" 1 ตัวหากการ์ดใบนี้สะสม \"Pigeon\" ได้ครบ 3 ตัว จะทิ้งการ์ดใบนี้: จั่วการ์ด 1 ใบ และทำให้เกิดธาตุสารพัดประโยชน์ 1 ลูก"
    },
    {
      "name": "",
      "desc": "ในแต่ละเทิร์นจะเกิดขึ้น 1 ครั้ง โดยอัตโนมัติ: การ์ดใบนี้จะสะสม \"Pigeon\" 1 ตัว หากการ์ดใบนี้สะสม \"Pigeon\" ได้ครบ 3 ตัว จะทิ้งการ์ดใบนี้: จั่วการ์ด 1 ใบ และทำให้เกิดธาตุสารพัดประโยชน์ 1 ลูก"
    }
  ],
  "version": "4.4",
  "shareId": 200
}