{
  "id": "ExilesCirclet",
  "shareId": 153,
  "name": "Corona dell'esule",
  "title": "Discesa nobile: Corona dell'esule",
  "desc": "\"Sventura a te, o grande sala dalle cataste d'argento! Perché la tua corona è intrisa di sangue?\"",
  "in_play_description": "Dopo che questo personaggio usa un Tripudio elementale: tutti i tuoi personaggi inattivi ottengono 1 punto Energia (una volta per turno).",
  "attributes": {
    "cost": 2,
    "cost_type": "elemento indefinito",
    "card_type": "Carta equipaggiamento",
    "energy": [
      {
        "id": "UnalignedElement",
        "type": "elemento indefinito",
        "count": 2
      }
    ],
    "artifact": {
      "id": "TheExile",
      "name": "The Exile",
      "rarity": 4
    },
    "tags": [
      "Manufatto"
    ]
  },
  "skills": [
    {
      "name": "",
      "desc": "Dopo che il personaggio usa un Tripudio elementale: tutti i tuoi personaggi inattivi ottengono 1 punto Energia (una volta per turno). (Il personaggio può equipaggiare un massimo di 1 manufatto.)"
    }
  ],
  "version": "3.4"
}