{
	"id": "ValleyStoreTheLeisureOfTea",
	"rarity": 4,
	"name": "Tal-Laden – „Die Muße des Tees“",
	"description": "Der offene Raum des Ladens in der zweiten Etage mit einer stabilen Plattform aus duftendem Zedernholz hat die gleiche Form wie das Hauptgebäude der „Teestube Jiulüe“ am Yilong-Pier.\\nDie charakteristische Architektur des Chenyu-Tals mit den weißen Wänden und schwarzen Kacheln ist für jeden Besucher, der zum ersten Mal hierherkommt, ein besonderer Anblick. Wenn man nicht weiß, wo man anfangen soll, besucht man am besten die Teestube Jiulüe und genießt eine Tasse Yauwan-Tee oder ein anderes typisches Getränk. Lass dich vom Tee leiten und lerne das Chenyu-Tal mit all seinen Schätzen in Ruhe kennen.",
	"load": 425,
	"energy": 90,
	"exp": 90,
	"category": [
		{
			"id": 13001,
			"category": "Liyue",
			"type": "Exterior"
		}
	],
	"recipe": [
		{
			"id": "FragrantCedarWood",
			"name": "Duftendes Zedernholz",
			"amount": 24
		}
	],
	"version": "4.4"
}
