{
  "id": "LithicSpear",
  "shareId": 138,
  "name": "Lanza Lítica",
  "title": "Inamovible como un peñasco: Lanza Lítica",
  "desc": "El arma predilecta por la Geoarmada de antaño. Una lanza excelentemente forjada con rocas del Bosque de Piedra Guyun. La robustez de su filo no tiene igual.",
  "in_play_description": "Daño +1.",
  "attributes": {
    "cost": 3,
    "cost_type": "Dados unielementales",
    "card_type": "Carta de equipamiento",
    "energy": [
      {
        "id": "MatchingElement",
        "type": "Dados unielementales",
        "count": 3
      }
    ],
    "tags": [
      "Arma",
      "Lanza"
    ]
  },
  "skills": [
    {
      "name": "",
      "desc": "El personaje inflige daño +1. Al entrar en el campo de batalla, por cada personaje de Liyue que haya en tu equipo, esta carta otorga 1 pt. de escudo al personaje que la lleve equipada (acumulable hasta 3 pts.). Solo pueden llevarla equipada los personajes que usan lanza. Cada personaje solo puede llevar equipada 1 arma."
    }
  ],
  "version": "3.4"
}