{
  "id": "JavelinImminent",
  "rarity": 3,
  "name": "\"หอกที่รอการปล่อย\"",
  "description": "หน้ากากที่มีรูปร่างคล้ายมงกุฎขนนก สามารถซื้อได้จากแผงลอยในตลาดนัด Chuwen ภายในลานประลองเพลิงศักดิ์สิทธิ์ ขนนกที่ปักอยู่บนหน้ากาก ทำให้นึกถึงปีกที่พร้อมจู่โจม ว่ากันว่า นักรบที่ชาญฉลาดจะกำหน้าหอกไว้ในมืออย่างแน่นหนา และสะสมพลังไว้ เมื่อศัตรูประมาทพลั้งเผลอ ก็จะปล่อยการโจมตีที่สำคัญที่สุดออกมา",
  "load": 85,
  "energy": 60,
  "exp": 60,
  "category": [
    {
      "id": 11002,
      "category": "เครื่องมือ"
    }
  ],
  "recipe": [
    {
      "id": "Fabric",
      "name": "ผ้า",
      "amount": 4
    },
    {
      "id": "YellowDye",
      "name": "สีย้อมสีเหลือง",
      "amount": 4
    }
  ],
  "version": "5.1"
}