{
  "id": "ShadeInTheTranquilCourt",
  "rarity": 3,
  "name": "Ombra nella corte tranquilla",
  "description": "Un edificio spazioso dotato di un peculiare soffitto a cupola, identico nell'aspetto e nella costruzione ai padiglioni nei pressi del Pardis Dhyai. Stando ai ricercatori della Kshahrewar, non solo questa forma è in grado di generare ombra, ma può anche alimentare il flusso d'aria nelle aree adiacenti, migliorando perfino il clima dell'intera regione. Non convinti di ciò, i ricercatori dell'Amurta hanno condotto degli esperimenti e scoperto che ,effettivamente, la Kshahrewar aveva ragione. Sfortunatamente, l'entità di tali effetti non è percepita dal corpo umano, e ancor meno dalle piante del Pardis Dhyai...",
  "load": 300,
  "energy": 60,
  "exp": 60,
  "category": [
    {
      "id": 13005,
      "category": "Sumeru",
      "type": "Exterior"
    }
  ],
  "recipe": [
    {
      "id": "WhiteIronChunk",
      "name": "Pezzo di ferro bianco",
      "amount": 4
    },
    {
      "id": "IronChunk",
      "name": "Pezzo di ferro",
      "amount": 4
    }
  ],
  "version": "4.3"
}